connect_RemoteDatabase/__init__.py
connect_RemoteDatabase/user_connect.py
connect_RemoteDatabase-2.0.0.dist-info/METADATA
connect_RemoteDatabase-2.0.0.dist-info/WHEEL
connect_RemoteDatabase-2.0.0.dist-info/top_level.txt
connect_RemoteDatabase-2.0.0.dist-info/RECORD
